suprconfig/__init__.py
suprconfig/config.py
suprconfig-0.9.dist-info/METADATA
suprconfig-0.9.dist-info/WHEEL
suprconfig-0.9.dist-info/top_level.txt
suprconfig-0.9.dist-info/RECORD
