Metadata-Version: 2.1
Name: suprconfig
Version: 0.9
Summary: This library created for comfortable using config
Author: h99hood
Author-email: keneskay@vk.com
